{
  "clearAll":"Limpar Tudo!",
  "noClear":"Você não pode limpar os dados salvos no jogo.\nVá para o menu",
  "paused":"Jogo em Pausa",
  "totalComp":"Conclusão Total",
  "back":"Voltar",
  "cleared":"LIMPO",
  "none":"NENHUM",
  "mainmenu":"Menu Principal",
  "quitAct":"Parar Ação",
  "resetAct":"Reiniciar Ação",
  "timePlayed":"Tempo de Jogo:",
  "progress":"Progresso:",
  "currRank":"Classificação Atual",
  "star":"Estrela",
  "fastestTime":"Melhor Tempo:",
  "hard":"Difícil",
  "goldSmall":"Ouro",

  "ui_achievement_title": "Conquistas desbloqueadas!",
  "challenge": "desafio",
  "ui_gp_hub_name_title": "O teu tempo",
  "ui_act_select_title": "Seleccionar acto",
  "deaths": "Mortes",
  "totalDeaths": "Total de mortes",
  "perfect": "PERFEITO",
  "gold": "OURO",
  "silver": "PRATA",
  "bronze": "BRONZE",
  "ui_mm_start": "Jogar",
  "ui_trophie_title": "Troféus",
  "ui_options_title": "Opções",
  "ui_trophie_section1_title": "Actos padrão",
  "ui_trophie_section2_title": "Hardcore",
  "ui_trophie_section3_title": "Coisas Incríveis",
  "ui_trophie_section4_title": "Conclusão",
  "trophie1":"Actos padrão: completar os actos padrão, 1 para a Vexation",
  "trophie2":"Hardcore: completar os actos de desafio e encontrar estrelas escondidas",
  "trophie3":"Coisas incríveis: realizar feitos difíceis e complicados",
  "trophie4":"Conclusão: um resumo das outras categorias",
  "trophieAct1":"Acto 1: completa o acto 1 para qualquer classificação",
  "trophieAct2":"Acto 2: completa o acto 2 para qualquer classificação",
  "trophieAct3":"Acto 3: completa o acto 3 para qualquer classificação",
  "trophieAct4":"Acto 4: completa o acto 4 para qualquer classificação",
  "trophieAct5":"Acto 5: completa o acto 5 para qualquer classificação",
  "trophieAct6":"Acto 6: completa o acto 6 para qualquer classificação",
  "trophieAct7":"Acto 7: completa o acto 7 para qualquer classificação",
  "trophieAct8":"Acto 8: completa o acto 8 para qualquer classificação",
  "trophieAct9":"Acto 9: completa o acto 9 para qualquer classificação",
  "trophieAct10":"Vexation: completa a 'Vexation' para qualquer classificação",
  "trophieStar1":"Minha! - Apanha a estrela escondida no acto 1",
  "trophieStar2":"Obrigado chefe! - Apanha a estrela escondida no acto 2",
  "trophieStar3":"É a subida! - Apanha a estrela escondida no acto 3",
  "trophieStar4":"Entre uma serra: apanha a estrela escondida no acto 4",
  "trophieStar5":"Salto de fé: apanha a estrela escondida no acto 5",
  "trophieStar6":"Chaveiro: apanha a estrela escondida no acto 6",
  "trophieStar7":"Corre o risco: - apanha a estrela escondida no acto 7",
  "trophieStar8":"Luzes apagadas! - Apanha a estrela escondida no acto 8",
  "trophieStar9":"Fora da caixa: apanha a estrela escondida no acto 9",
  "trophieStar10":"Dentro da caixa: apanha a estrela escondida na 'Vexation' ",
  "trophieHard1":"Um passo de cada vez: completa o modo de desafio para o acto 1",
  "trophieHard2":"Dobra a aposta: completa o modo de desafio para o acto 2",
  "trophieHard3":"A terceira é de vez: completa o modo de desafio para o acto 3",
  "trophieHard4":"Quarteto fantástico: completa o modo de desafio para o acto 4",
  "trophieHard5":"Bate cinco: completa o modo de desafio para o acto 5",
  "trophieHard6":"Demónio: completa o modo de desafio para o acto 6",
  "trophieHard7":"Estás com sorte: completa o modo de desafio para o acto 7",
  "trophieHard8":"Oito vezes campeão: completa o modo de desafio para o acto 8",
  "trophieHard9":"Nove vidas: completa o modo de desafio para o acto 9",
  "trophieAwesome1":"Perfeito! - Completa qualquer acto com classificação perfeita",
  "trophieAwesome2":"Zelador: segura 4 chaves ao mesmo tempo",
  "trophieAwesome3":"Afogando: vem à tona com uma bolha restante",
  "trophieAwesome4":"O tempo voa V 2.0: joga por mais de uma hora",
  "trophieAwesome5":"Olha para acima: esmagado por um bloco móvel",
  "trophieAwesome6":"Magnata da morte: obtém mais de 100 mortes totais",
  "trophieComplete1":"Olímpico: consegue ouro, ou mais, em cada acto",
  "trophieComplete2":"Perfeccionista: alcança a perfeição, ou mais, em cada acto",
  "trophieComplete3":"Astrónomo: colecta todas as estrelas do jogo",
  "trophieComplete4":"Vencedor: completa todos os actos no modo desafio",
  "trophieComplete5":"Dica: não gostas dos controlos? Podes mudá-los no menu de opções!",
  "musVol":"Volume da música",
  "sfxVol":"Volume dos efeitos",
  "particelLimit":"Limite de partículas",
  "autoReset":"Reinício automático quando o melhor tempo for ultrapassado",
  "blend":"Modo combinação",
  "parallax":"Paralaxe de dundo",
  "yes": "Sim",
  "no": "Não",
  "retry":"TENTAR NOVAMENTE",
  "youOk": "ESTÁS BEM?",
"language": "Linguagem",
"pressDown":"Carrega para baixo para entrar na fase",
  "pressDownEnter":"Carrega para baixo para entrar",
  "checkpoint":"PONTO DE CONTROLO!",
"acthub":"CENTRO DE NÍVEL",
  "act1":"ACTO 1",
  "act2":"ACTO 2",
  "act3":"ACTO 3",
  "act4":"ACTO 4",
  "act5":"ACTO 5",
  "act6":"ACTO 6",
  "act7":"ACTO 7",
  "act8":"ACTO 8",
  "act9":"ACTO 9",
  "act10":"VEX",
  "death0_1":"Cravado!",
  "death0_2":"Estourado!",
  "death1_1":"Salpicado!",
  "death1_2":"Aterragem forçada!",
  "death2_1":"Desfiado!",
  "death2_2":"Estraga-prazeres!",
  "death2_3":"Serrado em pedaços!",
  "death3_1":"Esmagado!",
  "death3_2":"Espremido!",
  "death3_3":"Muito comprimido!",
  "death4_1":"Os pulmões colapsaram!",
  "death4_2":"Afogado!",
  "death4_3":"Dormindo com os peixes...!",
  "death5_1":"Foi embora para sempre!",
  "death5_2":"Directo para o inferno!",
  "death5_3":"Caiu longe demais!",
  "death6_1":"Entrada proibida!",
  "death7_1":"Espremido.",
  "death7_2":"Espremido.",
  "death7_3":"Esmagado.",
  "death8_1":"Segado.",
  "death8_2":"Ceifado.",
  "death8_3":"Morte sombria.",
  "death8_4":"Decapitado.",
  "death9_1":"Tentou o shurikenjutsu!",
  "death9_2":"Ninja mau!",
  "death9_3":"Fatiado e picado!",
  "death10_1":"Morto por toda parte!",
  "death10_2":"Fatiado e picado!",
  "death11_1":"Eletrocutado!",
  "death11_2":"Chispado!",
  "death11_3":"Electrizante.",
  "death12_1":"Esmagado!",
  "death12_2":"Espremido!",
  "death12_3":"Muito comprimido!",
  "death13_1":"Varrido.",
  "death13_2":"Apressado.",
  "death13_3":"Rasgado em pedaços",
  "death14_1":"Obliterado!",
  "death14_2":"Respingado!",
  "death14_3":"Vexman frigido!",
  "death15_1":"Cravado por surpresa!",
  "death15_2":"Furado!",
  "tf1":"Bem-vindo de volta a [0]VEX[0]",
  "tf2":"Carrega [1]para baixo[1] para entrar no [1]Acto 1[1]",
  "tf3":"Podes voar com o [0]papagaio[0]!",
  "tf4":"Usa a tocha para fazer explodir TNT!",
  "tf5":"Não toques na água ou perderás a tua tocha",
  "tf6":"Joga novos [2]actos[2] parando nos seus [2]blocos[2] de actos",
  "tf7":"Salta de [3]um lado para o outro[3] para te levantares",
  "tf8":"Vamos recapitular desde o [2]Vex2[2]",
  "tf9":"Cuidado! Os blocos cinzas ligam e desligam",
  "tf10":"[2]Sigue[2] as [2]setas[2] para chegares ao fim",
  "tf11":"Enquanto corres, [2]mantém carregado[2] para [2]deslizar[2]!",
  "tf12":"Como antes, os blocos [4]roxos[4] blocos são bastante [4]fracos[4]",
  "tf13":"Move-te com as [5]setas direccionais[5] ou com [5]WASD[5]",
  "tf13Mob":"Toca nas [5]setas[5] para [5]MOVER[5]",
  "tf14":"Os blocos [6]laranja[6] fazem com que saltes muito alto!",
  "tf15":"Podes pegar um poste para deslizar para cima e para baixo",
  "tf16":"Esses portais vão te teletransportar para outro lugar no mapa",
  "tf18":"Estás [2]a ir bem [2] até agora!",
  "tf19":"Cuidado, as [7]quedas longas[7] podem-te matar!",
  "tf20":"Cuidado, estás a ficar [8]sem ar[8]! Nada [8]avançando[8] na direcção que tens à frente",
  "tf21":"Os blocos [9]castanhos[9] podem ser [8]empurrados[8] de qualquer maneira!",
  "tf22":"[8]Carrega para baixo[8] em um bloco preso para [8]expulsá-lo [8]",
  "tf23":"[10]Salta[10] enquanto estiveres na secção [11]vermelha[11] para balançar para a frente",
  "tf24":"[10]Saltando[10] na [12]secção azul[12] balanças ainda mais",
  "tf25":"[10]Muda a direcção[10] do teu balanço usando [10]esquerda[10] ou [10]direita[10]",
  "tf26":"O [13]gelo[13] é [13]escorregadio[13] e [13]derrete[13] com o tempo!",
  "tf27":"[10]Mantém pressionado[10] no ar para[10]chutar[10] e quebrar [14]vidro[14]",
  "tf28":"O [15]bloco de velocidade [15] move-te na direcção mostrada!",
  "tf29":"Para vencer os [15]lasers[15] tens que ser rápido!  Tenta usar a tua [16]habilidade de chute[16] [16]mantendo pressionado[16] no ar",
  "tf30":"Usa as [10]chaves[10] para desbloquear [17]blocos bloqueados[17]",
  "tf31":"O [18]portal[18] está no final dos [19]blocos bloqueados[19]!",
  "tf32":"Tens que [20]encontrar[20] as [10]chaves [10]!",
  "tf33":"[3]Pula[3] para o [21]canhão[21] e [3]carrega para cima[3] quando quiseres ser disparado!",
  "tf34":"Estas pequenas bolhas [22]recarregan[22] a tua respiração debaixo d'água!",
  "tf35":"Cuidado com a faísca ao redor da borda",
  "tf36":"Os [25]blocos solares[25] desaparecem quando a [26]luz[26] está desligada!",
  "tf37":"Se uma faísca toca a água, fica electrificada",
  "tf38":"Obrigado por jogar [29]Vex 3[29]! Estás quase a acabar...",
  "tf39":"Os blocos [30]cor-de-rosa[30] viram [31]invisíveis[31] quanto mais perto te chegas",
  "tf40":"As teclas [11]vermelhas[11] desaparecem após 5 segundos",
  "tf41":"Podes [32]dar uma vista de olhos[32] à cena enquanto [32]estás parado[32]",
  "tf42":"Ora, o [33] teste final [33]. Se o fio te bater até o fim, terás que [33]refazer todo o acto[33]!",
  "tf43":"Caminho errado, parvo!",
  "tf44":"Bom trabalho! Agora vá encontrar o [34]próximo acto[34]",
  "tf45":"Apanha [35]3 estrelas[35] no [35]Acto 1[35] para desbloquear o [35]modo difícil[35]"
}